<Properties StartupConfiguration="{32735DBE-EA04-BA93-51D8-1BE73F9E6252}|">
  <MonoDevelop.Ide.Workbench />
  <MonoDevelop.Ide.DebuggingService.PinnedWatches />
  <MonoDevelop.Ide.Workspace ActiveConfiguration="Debug" />
  <MonoDevelop.Ide.ItemProperties.Assembly-CSharp PreferredExecutionTarget="4fb919ba-6837-4f09-a6f2-9a21576f149e" />
  <MonoDevelop.Ide.DebuggingService.Breakpoints>
    <BreakpointStore />
  </MonoDevelop.Ide.DebuggingService.Breakpoints>
  <MultiItemStartupConfigurations />
</Properties>